pysyllable/__init__.py
pysyllable/problematic.py
pysyllable-0.0.1.dist-info/LICENSE
pysyllable-0.0.1.dist-info/METADATA
pysyllable-0.0.1.dist-info/WHEEL
pysyllable-0.0.1.dist-info/top_level.txt
pysyllable-0.0.1.dist-info/RECORD
