Metadata-Version: 2.1
Name: pysyllable
Version: 0.0.1
Summary: Syllable counter
Author-email: Michal Kouril <xmkouril@gmail.com>
Project-URL: Homepage, https://github.com/namelingo/pysyllable
Project-URL: Issues, https://github.com/namelingo/pysyllable/issues
Classifier: Programming Language :: Python :: 3
Classifier: License :: OSI Approved :: MIT License
Classifier: Operating System :: OS Independent
Requires-Python: >=3.8
License-File: LICENSE
